{"stat.useItem.minecraft.bow":21,"stat.pickup.minecraft.wooden_slab":3,"stat.leaveGame":27,"stat.craftItem.minecraft.iron_axe":9,"stat.mineBlock.minecraft.sandstone":58,"stat.useItem.minecraft.planks":193,"stat.craftItem.minecraft.shield":1,"stat.useItem.minecraft.nether_brick_stairs":21,"stat.pickup.minecraft.glass":9,"stat.useItem.minecraft.water_bucket":72,"stat.mineBlock.minecraft.stone_brick_stairs":142,"stat.pickup.minecraft.sand":166,"achievement.diamonds":23,"stat.pickup.minecraft.cobblestone_wall":44,"stat.pickup.minecraft.bucket":1,"stat.useItem.minecraft.rail":499,"stat.mineBlock.minecraft.wooden_slab":63,"stat.craftItem.minecraft.iron_shovel":35,"stat.mineBlock.minecraft.snow_layer":2,"stat.pickup.minecraft.brown_mushroom":3,"achievement.buildPickaxe":98,"stat.mineBlock.minecraft.sand":142,"stat.killEntity.Witch":1,"achievement.buildBetterPickaxe":96,"stat.useItem.minecraft.fence_gate":9,"stat.useItem.minecraft.iron_pickaxe":7307,"stat.craftItem.minecraft.wooden_pickaxe":2,"stat.useItem.minecraft.iron_shovel":4965,"stat.pickup.minecraft.double_plant":7,"stat.craftItem.minecraft.hardened_clay":64,"stat.useItem.minecraft.oak_stairs":8,"stat.furnaceInteraction":306,"stat.mineBlock.minecraft.rail":33,"stat.useItem.minecraft.pumpkin_seeds":6,"stat.pickup.minecraft.fence_gate":10,"stat.useItem.minecraft.minecart":41,"stat.useItem.minecraft.double_plant":11,"stat.pickup.minecraft.furnace":3,"stat.useItem.minecraft.redstone":8,"achievement.mineWood":673,"stat.pickup.minecraft.iron_chestplate":1,"stat.useItem.minecraft.fence":88,"achievement.openInventory":1809,"stat.pickup.minecraft.stone_stairs":2,"stat.pickup.minecraft.potion":3,"stat.mineBlock.minecraft.fence":88,"stat.useItem.minecraft.wheat_seeds":236,"stat.mineBlock.minecraft.soul_sand":132,"stat.mineBlock.minecraft.oak_stairs":10,"stat.deaths":6,"stat.pickup.minecraft.egg":51,"stat.craftItem.minecraft.melon_seeds":35,"stat.playOneMinute":5230509,"stat.mineBlock.minecraft.stone_pressure_plate":3,"stat.craftItem.minecraft.iron_pickaxe":44,"stat.mineBlock.minecraft.tallgrass":121,"stat.chestOpened":455,"stat.craftItem.minecraft.sign":5,"stat.useItem.minecraft.stone":16,"stat.mineBlock.minecraft.netherrack":405,"stat.pickup.minecraft.waterlily":1,"stat.pickup.minecraft.wooden_pressure_plate":10,"stat.craftItem.minecraft.redstone_torch":26,"stat.craftItem.minecraft.golden_rail":24,"stat.pickup.minecraft.detector_rail":2,"stat.craftItem.minecraft.coal":37,"stat.drop.minecraft.iron_pickaxe":1,"stat.craftItem.minecraft.iron_hoe":3,"stat.fallOneCm":324634,"stat.pickup.minecraft.carrot":127,"stat.pickup.minecraft.melon_seeds":16,"stat.crouchOneCm":63442,"achievement.killCow":2,"stat.mineBlock.minecraft.chest":7,"stat.pickup.minecraft.rail":246,"stat.craftItem.minecraft.iron_ingot":525,"stat.pickup.minecraft.melon":111,"stat.useItem.minecraft.iron_hoe":338,"stat.craftingTableInteraction":170,"stat.mineBlock.minecraft.wooden_pressure_plate":12,"stat.useItem.minecraft.golden_rail":24,"stat.pickup.minecraft.feather":3,"stat.useItem.minecraft.furnace":9,"stat.craftItem.minecraft.nether_brick":80,"stat.pickup.minecraft.dye":142,"stat.pickup.minecraft.planks":18,"stat.pickup.minecraft.iron_leggings":1,"stat.pickup.minecraft.wheat_seeds":114,"stat.mineBlock.minecraft.gravel":702,"stat.craftItem.minecraft.iron_leggings":1,"stat.useItem.minecraft.wool":3,"stat.mineBlock.minecraft.dirt":4390,"stat.pickup.minecraft.poisonous_potato":1,"stat.useItem.minecraft.torch":919,"stat.craftItem.minecraft.redstone_block":37,"stat.useItem.minecraft.log":6,"stat.pickup.minecraft.crafting_table":5,"stat.useItem.minecraft.cobblestone":906,"stat.craftItem.minecraft.crafting_table":3,"stat.useItem.minecraft.gravel":29,"stat.mineBlock.minecraft.double_plant":6,"stat.pickup.minecraft.iron_hoe":1,"stat.minecartOneCm":3040001,"stat.mineBlock.minecraft.emerald_ore":4,"stat.pickup.minecraft.log":46,"stat.pickup.minecraft.iron_pickaxe":3,"stat.craftItem.minecraft.stone_button":3,"stat.mineBlock.minecraft.golden_rail":2,"stat.useItem.minecraft.yellow_flower":6,"stat.craftItem.minecraft.gold_ingot":42,"stat.pickup.minecraft.chicken":3,"stat.pickup.minecraft.sapling":11,"stat.pickup.minecraft.wooden_door":12,"achievement.portal":10,"stat.craftItem.minecraft.planks":490,"stat.useItem.minecraft.iron_sword":153,"stat.itemEnchanted":7,"stat.useItem.minecraft.wooden_pressure_plate":11,"stat.useItem.minecraft.stonebrick":413,"stat.mineBlock.minecraft.log":296,"stat.craftItem.minecraft.wooden_door":3,"stat.craftItem.minecraft.cooked_chicken":33,"stat.mineBlock.minecraft.waterlily":1,"stat.useItem.minecraft.wooden_door":18,"achievement.acquireIron":91,"stat.pickup.minecraft.iron_door":2,"stat.pickup.minecraft.red_flower":19,"stat.sneakTime":24132,"stat.pickup.minecraft.wool":5,"stat.mineBlock.minecraft.cobblestone_wall":239,"stat.useItem.minecraft.baked_potato":2,"stat.pickup.minecraft.stone_slab":1,"stat.pickup.minecraft.yellow_flower":3,"stat.pickup.minecraft.golden_rail":10,"stat.pickup.minecraft.chest":8,"stat.pickup.minecraft.stone_pressure_plate":3,"stat.pickup.minecraft.redstone_torch":9,"stat.horseOneCm":737662,"stat.useItem.minecraft.iron_axe":1048,"stat.mineBlock.minecraft.cobblestone":243,"stat.pickup.minecraft.flint":46,"stat.mineBlock.minecraft.yellow_flower":4,"stat.entityKilledBy.Witch":1,"stat.craftItem.minecraft.stone_brick_stairs":590,"stat.mineBlock.minecraft.brown_mushroom":1,"stat.craftItem.minecraft.iron_trapdoor":1,"stat.swimOneCm":496410,"stat.climbOneCm":437456,"achievement.buildWorkBench":11,"stat.craftItem.minecraft.gold_block":2,"stat.drop.minecraft.brown_mushroom":1,"stat.breakItem.minecraft.iron_pickaxe":1,"stat.useItem.minecraft.redstone_torch":20,"stat.useItem.minecraft.dirt":1105,"achievement.exploreAllBiomes":{"value":0,"progress":["Cold Taiga","Birch Forest","Roofed Forest","Beach","FrozenRiver","Extreme Hills+","Cold Beach","Ocean","River","Taiga","Swampland","Ice Mountains","Birch Forest Hills","ForestHills","Plains","Extreme Hills Edge","DesertHills","Ice Plains","Jungle","Forest","JungleHills","Desert","Extreme Hills","Hell","Deep Ocean"]},"stat.pickup.minecraft.iron_boots":1,"stat.craftItem.minecraft.furnace":1,"stat.useItem.minecraft.red_flower":39,"stat.craftItem.minecraft.lapis_block":31,"stat.mineBlock.minecraft.detector_rail":1,"stat.useItem.minecraft.egg":55,"stat.craftItem.minecraft.iron_boots":1,"stat.useItem.minecraft.detector_rail":3,"stat.craftItem.minecraft.cooked_beef":2,"stat.pickup.minecraft.cobblestone":2980,"stat.mineBlock.minecraft.clay":2,"stat.flyOneCm":472326,"stat.craftItem.minecraft.glass_bottle":60,"stat.pickup.minecraft.sandstone":58,"stat.craftItem.minecraft.wooden_slab":144,"stat.pickup.minecraft.redstone":334,"stat.mineBlock.minecraft.iron_ore":268,"stat.timeSinceDeath":128707,"stat.useItem.minecraft.sign":6,"stat.useItem.minecraft.wooden_slab":226,"stat.useItem.minecraft.iron_door":2,"stat.craftItem.minecraft.iron_block":8,"stat.killEntity.Bat":5,"stat.craftItem.minecraft.stonebrick":1502,"stat.useItem.minecraft.lever":1,"stat.useItem.minecraft.potato":71,"stat.pickup.minecraft.stonebrick":29,"stat.pickup.minecraft.iron_shovel":3,"stat.mineBlock.minecraft.coal_ore":1100,"stat.killEntity.Creeper":7,"stat.talkedToVillager":1,"stat.mineBlock.minecraft.ladder":30,"achievement.buildSword":2,"stat.sprintOneCm":2125953,"stat.mineBlock.minecraft.stone_slab":20,"stat.craftItem.minecraft.stick":666,"stat.useItem.minecraft.stone_slab":29,"stat.craftItem.minecraft.stained_hardened_clay":4,"stat.craftItem.minecraft.stone":1323,"stat.mineBlock.minecraft.diamond_ore":16,"stat.mineBlock.minecraft.crafting_table":10,"stat.useItem.minecraft.stone_pressure_plate":3,"stat.useItem.minecraft.carrot":33,"stat.craftItem.minecraft.wooden_pressure_plate":1,"stat.useItem.minecraft.bucket":85,"achievement.killEnemy":35,"achievement.buildFurnace":4,"stat.mineBlock.minecraft.planks":36,"stat.drop":531,"stat.pickup.minecraft.stone_button":1,"stat.breakItem.minecraft.iron_shovel":1,"stat.useItem.minecraft.ladder":106,"stat.useItem.minecraft.melon_seeds":19,"stat.killEntity.Zombie":14,"stat.craftItem.minecraft.dye":5,"stat.mineBlock.minecraft.gold_ore":33,"stat.diveOneCm":262806,"stat.pickup.minecraft.wheat":65,"stat.craftItem.minecraft.piston":1,"stat.craftItem.minecraft.ladder":111,"achievement.buildHoe":3,"stat.pickup.minecraft.sign":1,"stat.mineBlock.minecraft.stone_button":7,"stat.pickup.minecraft.gravel":449,"stat.craftItem.minecraft.cooked_porkchop":11,"stat.useItem.minecraft.glass_bottle":54,"stat.mineBlock.minecraft.deadbush":1,"stat.pickup.minecraft.stone_brick_stairs":31,"stat.jump":33117,"stat.useItem.minecraft.iron_trapdoor":4,"stat.useItem.minecraft.sand":7,"stat.pickup.minecraft.fence":88,"stat.pickup.minecraft.coal":1026,"stat.pickup.minecraft.iron_helmet":1,"stat.pickup.minecraft.iron_ingot":21,"stat.craftItem.minecraft.lever":1,"stat.useItem.minecraft.piston":8,"stat.craftItem.minecraft.torch":720,"stat.useItem.minecraft.stone_button":11,"stat.pickup.minecraft.dirt":1560,"stat.craftItem.minecraft.iron_helmet":1,"stat.craftItem.minecraft.rail":584,"stat.useItem.minecraft.cooked_chicken":27,"stat.pickup.minecraft.iron_ore":186,"stat.boatOneCm":2044,"stat.useItem.minecraft.sapling":8,"stat.pickup.minecraft.gold_ore":13,"stat.mineBlock.minecraft.lapis_ore":25,"stat.pickup.minecraft.iron_axe":2,"stat.mineBlock.minecraft.glass_pane":4,"stat.mineBlock.minecraft.stone_stairs":4,"stat.damageTaken":32845,"stat.drop.minecraft.iron_hoe":1,"stat.useItem.minecraft.stone_brick_stairs":784,"stat.mineBlock.minecraft.furnace":7,"stat.mineBlock.minecraft.torch":107,"stat.mineBlock.minecraft.red_flower":21,"stat.mineBlock.minecraft.melon_block":24,"stat.useItem.minecraft.wooden_pickaxe":40,"stat.mineBlock.minecraft.sapling":4,"stat.craftItem.minecraft.netherbrick":320,"stat.mineBlock.minecraft.fence_gate":14,"stat.pickup.minecraft.potato":80,"stat.pickup.minecraft.oak_stairs":10,"stat.damageDealt":13605,"stat.craftItem.minecraft.glass":169,"stat.craftItem.minecraft.baked_potato":66,"stat.mineBlock.minecraft.nether_brick_stairs":21,"stat.killEntity.Cow":3,"stat.useItem.minecraft.crafting_table":13,"stat.pickup.minecraft.minecart":22,"stat.killEntity.Pig":5,"stat.craftItem.minecraft.iron_sword":2,"stat.craftItem.minecraft.stone_slab":174,"stat.walkOneCm":23206912,"stat.useItem.minecraft.chest":2,"stat.pickup.minecraft.stick":12,"stat.pickup.minecraft.clay_ball":8,"stat.useItem.minecraft.lava_bucket":11,"stat.pickup.minecraft.stone":3,"stat.craftItem.minecraft.iron_chestplate":1,"stat.mineBlock.minecraft.wool":9,"stat.useItem.minecraft.stained_hardened_clay":2,"stat.craftItem.minecraft.redstone":45,"stat.craftItem.minecraft.minecart":1,"stat.pickup.minecraft.ladder":59,"stat.useItem.minecraft.netherrack":68,"stat.pickup.minecraft.gold_ingot":23,"stat.killEntity.Skeleton":10,"stat.mineBlock.minecraft.stonebrick":54,"stat.killEntity.Chicken":59,"stat.mineBlock.minecraft.redstone_torch":2,"stat.killEntity.Spider":3,"stat.mineBlock.minecraft.quartz_ore":1,"stat.pickup.minecraft.bread":1,"stat.mobKills":107,"stat.breakItem.minecraft.iron_axe":1,"stat.pickup.minecraft.water_bucket":3,"stat.useItem.minecraft.cobblestone_wall":1,"stat.pickup.minecraft.diamond":16,"stat.mineBlock.minecraft.leaves":1060,"stat.mineBlock.minecraft.piston":7,"stat.pickup.minecraft.torch":95,"stat.craftItem.minecraft.nether_brick_stairs":46,"stat.mineBlock.minecraft.redstone_ore":74,"stat.craftItem.minecraft.coal_block":88,"stat.craftItem.minecraft.brick":8,"stat.mineBlock.minecraft.stone":4518,"stat.useItem.minecraft.sandstone":30}