{"stat.damageDealt":2590,"achievement.exploreAllBiomes":{"value":0,"progress":["Extreme Hills+","Desert","Taiga","Ocean","Extreme Hills","Plains","FrozenRiver","Ice Plains","Ice Mountains","Jungle","Extreme Hills Edge","Birch Forest Hills","Hell","ForestHills","Cold Taiga","Forest","JungleHills","DesertHills","Beach","Birch Forest","Roofed Forest","River","Swampland"]},"stat.killEntity.Bat":3,"achievement.acquireIron":66,"stat.killEntity.Cow":1,"achievement.openInventory":1042,"stat.fallOneCm":199739,"achievement.portal":4,"stat.flyOneCm":259226,"achievement.buildWorkBench":8,"achievement.buildPickaxe":52,"stat.climbOneCm":274879,"achievement.buildFurnace":3,"stat.drop":528,"stat.killEntity.Chicken":39,"stat.damageTaken":29390,"stat.timeSinceDeath":12120,"achievement.diamonds":8,"stat.leaveGame":1,"stat.diveOneCm":178926,"stat.craftItem.minecraft.iron_ingot":2,"achievement.mineWood":395,"achievement.buildBetterPickaxe":52,"stat.playOneMinute":2960396,"stat.boatOneCm":2044,"stat.deaths":2,"stat.jump":19217,"stat.craftItem.minecraft.hardened_clay":64,"stat.swimOneCm":263483,"stat.mobKills":43,"stat.horseOneCm":732375,"stat.walkOneCm":13356966,"stat.minecartOneCm":1847664,"stat.sprintOneCm":6083}